dumbpm/__init__.py
dumbpm/cmd.py
dumbpm/est/__init__.py
dumbpm/est/est.py
dumbpm/est/parse.py
dumbpm/guess/__init__.py
dumbpm/guess/guess.py
dumbpm/guess/parse.py
dumbpm/prio/__init__.py
dumbpm/prio/parse.py
dumbpm/prio/prio.py
dumbpm/shared/__init__.py
dumbpm/shared/shared.py
dumbpm-0.8.1.dist-info/entry_points.txt
dumbpm-0.8.1.dist-info/LICENSE
dumbpm-0.8.1.dist-info/WHEEL
dumbpm-0.8.1.dist-info/METADATA
dumbpm-0.8.1.dist-info/RECORD
