Metadata-Version: 2.1
Name: dumbpm
Version: 0.8.1
Summary: A pretty dumb PM.
Home-page: https://github.com/poros/dumbpm
License: Apache-2.0
Keywords: project management,agile,estimate,PM
Author: Antonio Uccio Verardi
Author-email: antonio.uccio.verardi@gmail.com
Requires-Python: >=3.9,<4.0
Classifier: License :: OSI Approved :: Apache Software License
Classifier: Programming Language :: Python :: 3
Classifier: Programming Language :: Python :: 3.10
Classifier: Programming Language :: Python :: 3.9
Requires-Dist: numpy
Requires-Dist: pandas
Requires-Dist: scipy
Project-URL: Documentation, https://poros.github.io/dumbpm/
Project-URL: Repository, https://github.com/poros/dumbpm
